commonutil_interpolatetext/__init__.py
commonutil_interpolatetext/_base.py
commonutil_interpolatetext/pipeableregexmatch.py
commonutil_interpolatetext/py.typed
commonutil_interpolatetext/regexmatch.py
commonutil_interpolatetext-3.0.3.dist-info/METADATA
commonutil_interpolatetext-3.0.3.dist-info/WHEEL
commonutil_interpolatetext-3.0.3.dist-info/top_level.txt
commonutil_interpolatetext-3.0.3.dist-info/RECORD
